{
  "Event Weapon": {
    "banners.weponbox_1_2_2": {
      "Total Users": 2,
      "Total Pulls": 130,
      "Oroberyl Spent": null,
      "6-Star": {
        "Rate": "5.385%",
        "Count": 7,
        "Median Pity": 15,
        "Won": "29%"
      },
      "5-Star": {
        "Rate": "19.231%",
        "Count": 25
      },
      "Total Obtained": 2,
      "Featured Image": null
    },
    "banners.weponbox_1_2_3": {
      "Total Users": 7,
      "Total Pulls": 450,
      "Oroberyl Spent": null,
      "6-Star": {
        "Rate": "4.667%",
        "Count": 21,
        "Median Pity": 19,
        "Won": "17%"
      },
      "5-Star": {
        "Rate": "14.000%",
        "Count": 63
      },
      "Total Obtained": 6,
      "Featured Image": null
    },
    "Drifting Raft Issue": {
      "Total Users": 1057,
      "Total Pulls": 65070,
      "Oroberyl Spent": null,
      "6-Star": {
        "Rate": "5.119%",
        "Count": 3331,
        "Median Pity": 14,
        "Won": "24%"
      },
      "5-Star": {
        "Rate": "17.118%",
        "Count": 11139
      },
      "Total Obtained": 978,
      "Featured Image": null
    },
    "Lupine Scarlet": {
      "Total Users": 1007,
      "Total Pulls": 57295,
      "Oroberyl Spent": null,
      "6-Star": {
        "Rate": "5.034%",
        "Count": 2884,
        "Median Pity": 15,
        "Won": "24%"
      },
      "5-Star": {
        "Rate": "17.036%",
        "Count": 9761
      },
      "Total Obtained": 883,
      "Featured Image": null
    },
    "Brigand's Calling": {
      "Total Users": 1210,
      "Total Pulls": 63630,
      "Oroberyl Spent": null,
      "6-Star": {
        "Rate": "5.180%",
        "Count": 3296,
        "Median Pity": 15,
        "Won": "26%"
      },
      "5-Star": {
        "Rate": "16.909%",
        "Count": 10759
      },
      "Total Obtained": 1065,
      "Featured Image": null
    },
    "Graffiti Issue": {
      "Total Users": 1533,
      "Total Pulls": 83238,
      "Oroberyl Spent": null,
      "6-Star": {
        "Rate": "5.150%",
        "Count": 4287,
        "Median Pity": 14,
        "Won": "22%"
      },
      "5-Star": {
        "Rate": "17.204%",
        "Count": 14320
      },
      "Total Obtained": 1364,
      "Featured Image": null
    },
    "Express Delivery Issue": {
      "Total Users": 2396,
      "Total Pulls": 119403,
      "Oroberyl Spent": null,
      "6-Star": {
        "Rate": "5.095%",
        "Count": 6083,
        "Median Pity": 14,
        "Won": "26%"
      },
      "5-Star": {
        "Rate": "17.071%",
        "Count": 20383
      },
      "Total Obtained": 1995,
      "Featured Image": null
    },
    "Smelting Forge Issue": {
      "Total Users": 2915,
      "Total Pulls": 197581,
      "Oroberyl Spent": null,
      "6-Star": {
        "Rate": "5.234%",
        "Count": 10341,
        "Median Pity": 14,
        "Won": "25%"
      },
      "5-Star": {
        "Rate": "17.122%",
        "Count": 33830
      },
      "Total Obtained": 3371,
      "Featured Image": null
    }
  }
}