{
  "Event Weapon": {
    "Smelting Fire Issue": {
      "Total Users": 25,
      "Total Pulls": 1370,
      "Oroberyl Spent": null,
      "6-Star": {
        "Rate": "4.672%",
        "Count": 64,
        "Median Pity": 15,
        "Won": "29%"
      },
      "5-Star": {
        "Rate": "17.737%",
        "Count": 243
      },
      "Total Obtained": 22,
      "Featured Image": null
    },
    "Swift Walker Issue": {
      "Total Users": 42,
      "Total Pulls": 2270,
      "Oroberyl Spent": null,
      "6-Star": {
        "Rate": "5.374%",
        "Count": 122,
        "Median Pity": 14,
        "Won": "23%"
      },
      "5-Star": {
        "Rate": "16.520%",
        "Count": 375
      },
      "Total Obtained": 39,
      "Featured Image": null
    },
    "Drifting Raft Issue": {
      "Total Users": 1288,
      "Total Pulls": 80870,
      "Oroberyl Spent": null,
      "6-Star": {
        "Rate": "5.154%",
        "Count": 4168,
        "Median Pity": 14,
        "Won": "24%"
      },
      "5-Star": {
        "Rate": "17.066%",
        "Count": 13801
      },
      "Total Obtained": 1244,
      "Featured Image": null
    },
    "Lupine Scarlet": {
      "Total Users": 1166,
      "Total Pulls": 66775,
      "Oroberyl Spent": null,
      "6-Star": {
        "Rate": "5.021%",
        "Count": 3353,
        "Median Pity": 15,
        "Won": "24%"
      },
      "5-Star": {
        "Rate": "17.122%",
        "Count": 11433
      },
      "Total Obtained": 1036,
      "Featured Image": null
    },
    "Brigand's Calling": {
      "Total Users": 1378,
      "Total Pulls": 72880,
      "Oroberyl Spent": null,
      "6-Star": {
        "Rate": "5.180%",
        "Count": 3775,
        "Median Pity": 14,
        "Won": "26%"
      },
      "5-Star": {
        "Rate": "16.894%",
        "Count": 12312
      },
      "Total Obtained": 1230,
      "Featured Image": null
    },
    "Graffiti Issue": {
      "Total Users": 1675,
      "Total Pulls": 92432,
      "Oroberyl Spent": null,
      "6-Star": {
        "Rate": "5.138%",
        "Count": 4749,
        "Median Pity": 14,
        "Won": "22%"
      },
      "5-Star": {
        "Rate": "17.204%",
        "Count": 15902
      },
      "Total Obtained": 1511,
      "Featured Image": null
    },
    "Express Delivery Issue": {
      "Total Users": 2520,
      "Total Pulls": 125954,
      "Oroberyl Spent": null,
      "6-Star": {
        "Rate": "5.094%",
        "Count": 6416,
        "Median Pity": 14,
        "Won": "26%"
      },
      "5-Star": {
        "Rate": "17.104%",
        "Count": 21543
      },
      "Total Obtained": 2110,
      "Featured Image": null
    },
    "Smelting Forge Issue": {
      "Total Users": 3034,
      "Total Pulls": 205625,
      "Oroberyl Spent": null,
      "6-Star": {
        "Rate": "5.225%",
        "Count": 10743,
        "Median Pity": 14,
        "Won": "26%"
      },
      "5-Star": {
        "Rate": "17.123%",
        "Count": 35210
      },
      "Total Obtained": 3517,
      "Featured Image": null
    }
  }
}