{
  "Special Headhunting": {
    "Thunder of Renewal": {
      "Total Users": 1397,
      "Total Pulls": 152914,
      "Oroberyl Spent": 76457000,
      "6-Star": {
        "Rate": "1.921%",
        "Count": 2938,
        "Median Pity": 44,
        "Won": "50%"
      },
      "5-Star": {
        "Rate": "12.086%",
        "Count": 18481
      },
      "Total Obtained": 1652,
      "Featured Image": "https://goyfield.moe/images/operators/preview/zhuangfy.png"
    },
    "Wolf Pearl": {
      "Total Users": 1749,
      "Total Pulls": 133788,
      "Oroberyl Spent": 66894000,
      "6-Star": {
        "Rate": "1.843%",
        "Count": 2466,
        "Median Pity": 35,
        "Won": "52%"
      },
      "5-Star": {
        "Rate": "12.039%",
        "Count": 16107
      },
      "Total Obtained": 1443,
      "Featured Image": "https://goyfield.moe/images/operators/preview/rossi.png"
    },
    "River's Daughter": {
      "Total Users": 1972,
      "Total Pulls": 148158,
      "Oroberyl Spent": 74079000,
      "6-Star": {
        "Rate": "1.866%",
        "Count": 2765,
        "Median Pity": 36,
        "Won": "50%"
      },
      "5-Star": {
        "Rate": "12.009%",
        "Count": 17792
      },
      "Total Obtained": 1587,
      "Featured Image": "https://goyfield.moe/images/operators/preview/tangtang.png"
    },
    "Hues Of Passion": {
      "Total Users": 2724,
      "Total Pulls": 182958,
      "Oroberyl Spent": 91479000,
      "6-Star": {
        "Rate": "1.683%",
        "Count": 3079,
        "Median Pity": 31,
        "Won": "50%"
      },
      "5-Star": {
        "Rate": "11.924%",
        "Count": 21816
      },
      "Total Obtained": 1758,
      "Featured Image": "https://goyfield.moe/images/operators/preview/yvonne.png"
    },
    "The Floaty Messenger": {
      "Total Users": 3712,
      "Total Pulls": 304450,
      "Oroberyl Spent": 152225000,
      "6-Star": {
        "Rate": "1.811%",
        "Count": 5513,
        "Median Pity": 34,
        "Won": "50%"
      },
      "5-Star": {
        "Rate": "12.118%",
        "Count": 36892
      },
      "Total Obtained": 3164,
      "Featured Image": "https://goyfield.moe/images/operators/preview/gilberta.png"
    },
    "Scars Of The Forge": {
      "Total Users": 3482,
      "Total Pulls": 354645,
      "Oroberyl Spent": 177322500,
      "6-Star": {
        "Rate": "1.715%",
        "Count": 6083,
        "Median Pity": 46,
        "Won": "52%"
      },
      "5-Star": {
        "Rate": "12.320%",
        "Count": 43694
      },
      "Total Obtained": 3639,
      "Featured Image": "https://goyfield.moe/images/operators/preview/laevatain.png"
    }
  }
}