{
  "Special Headhunting": {
    "banners.special_1_2_1": {
      "Total Users": 607,
      "Total Pulls": 58704,
      "Oroberyl Spent": 29352000,
      "6-Star": {
        "Rate": "2.002%",
        "Count": 1175,
        "Median Pity": 35,
        "Won": "53%"
      },
      "5-Star": {
        "Rate": "11.977%",
        "Count": 7031
      },
      "Total Obtained": 673,
      "Featured Image": "https://goyfield.moe/images/operators/preview/zhuangfy.png"
    },
    "Wolf Pearl": {
      "Total Users": 1058,
      "Total Pulls": 81145,
      "Oroberyl Spent": 40572500,
      "6-Star": {
        "Rate": "1.897%",
        "Count": 1539,
        "Median Pity": 29,
        "Won": "52%"
      },
      "5-Star": {
        "Rate": "11.986%",
        "Count": 9726
      },
      "Total Obtained": 893,
      "Featured Image": "https://goyfield.moe/images/operators/preview/rossi.png"
    },
    "River's Daughter": {
      "Total Users": 1303,
      "Total Pulls": 98116,
      "Oroberyl Spent": 49058000,
      "6-Star": {
        "Rate": "1.891%",
        "Count": 1855,
        "Median Pity": 32,
        "Won": "50%"
      },
      "5-Star": {
        "Rate": "11.968%",
        "Count": 11743
      },
      "Total Obtained": 1057,
      "Featured Image": "https://goyfield.moe/images/operators/preview/tangtang.png"
    },
    "Hues Of Passion": {
      "Total Users": 2048,
      "Total Pulls": 137085,
      "Oroberyl Spent": 68542500,
      "6-Star": {
        "Rate": "1.693%",
        "Count": 2321,
        "Median Pity": 28,
        "Won": "51%"
      },
      "5-Star": {
        "Rate": "11.878%",
        "Count": 16283
      },
      "Total Obtained": 1341,
      "Featured Image": "https://goyfield.moe/images/operators/preview/yvonne.png"
    },
    "The Floaty Messenger": {
      "Total Users": 3044,
      "Total Pulls": 252748,
      "Oroberyl Spent": 126374000,
      "6-Star": {
        "Rate": "1.822%",
        "Count": 4606,
        "Median Pity": 32,
        "Won": "50%"
      },
      "5-Star": {
        "Rate": "12.131%",
        "Count": 30660
      },
      "Total Obtained": 2648,
      "Featured Image": "https://goyfield.moe/images/operators/preview/gilberta.png"
    },
    "Scars Of The Forge": {
      "Total Users": 2988,
      "Total Pulls": 309852,
      "Oroberyl Spent": 154926000,
      "6-Star": {
        "Rate": "1.716%",
        "Count": 5317,
        "Median Pity": 46,
        "Won": "52%"
      },
      "5-Star": {
        "Rate": "12.349%",
        "Count": 38264
      },
      "Total Obtained": 3165,
      "Featured Image": "https://goyfield.moe/images/operators/preview/laevatain.png"
    }
  }
}