{
  "Standard Weapon": {
    "Solid Ice Issue": {
      "Total Users": 1089,
      "Total Pulls": 45080,
      "Oroberyl Spent": null,
      "6-Star": {
        "Rate": "5.016%",
        "Count": 2261,
        "Median Pity": 13,
        "Won": "27%"
      },
      "5-Star": {
        "Rate": "16.937%",
        "Count": 7635
      },
      "Total Obtained": 744,
      "Featured Image": null
    },
    "Cosmic Voice Issue": {
      "Total Users": 2979,
      "Total Pulls": 38190,
      "Oroberyl Spent": null,
      "6-Star": {
        "Rate": "4.226%",
        "Count": 1614,
        "Median Pity": 6,
        "Won": "25%"
      },
      "5-Star": {
        "Rate": "16.536%",
        "Count": 6315
      },
      "Total Obtained": 422,
      "Featured Image": null
    },
    "Far Expedition Issue": {
      "Total Users": 969,
      "Total Pulls": 41065,
      "Oroberyl Spent": null,
      "6-Star": {
        "Rate": "4.965%",
        "Count": 2039,
        "Median Pity": 13,
        "Won": "26%"
      },
      "5-Star": {
        "Rate": "16.812%",
        "Count": 6904
      },
      "Total Obtained": 642,
      "Featured Image": null
    },
    "Rising Mount Issue": {
      "Total Users": 379,
      "Total Pulls": 13755,
      "Oroberyl Spent": null,
      "6-Star": {
        "Rate": "5.009%",
        "Count": 689,
        "Median Pity": 12,
        "Won": "23%"
      },
      "5-Star": {
        "Rate": "16.510%",
        "Count": 2271
      },
      "Total Obtained": 193,
      "Featured Image": null
    },
    "Thunderous Peal Issue": {
      "Total Users": 269,
      "Total Pulls": 9790,
      "Oroberyl Spent": null,
      "6-Star": {
        "Rate": "4.566%",
        "Count": 447,
        "Median Pity": 12,
        "Won": "24%"
      },
      "5-Star": {
        "Rate": "16.609%",
        "Count": 1626
      },
      "Total Obtained": 132,
      "Featured Image": null
    }
  }
}