{
  "Standard Weapon": {
    "Solid Ice Issue": {
      "Total Users": 1119,
      "Total Pulls": 46110,
      "Oroberyl Spent": null,
      "6-Star": {
        "Rate": "5.012%",
        "Count": 2311,
        "Median Pity": 13,
        "Won": "27%"
      },
      "5-Star": {
        "Rate": "16.923%",
        "Count": 7803
      },
      "Total Obtained": 761,
      "Featured Image": null
    },
    "Cosmic Voice Issue": {
      "Total Users": 3048,
      "Total Pulls": 39120,
      "Oroberyl Spent": null,
      "6-Star": {
        "Rate": "4.225%",
        "Count": 1653,
        "Median Pity": 6,
        "Won": "25%"
      },
      "5-Star": {
        "Rate": "16.564%",
        "Count": 6480
      },
      "Total Obtained": 434,
      "Featured Image": null
    },
    "Far Expedition Issue": {
      "Total Users": 993,
      "Total Pulls": 42095,
      "Oroberyl Spent": null,
      "6-Star": {
        "Rate": "4.986%",
        "Count": 2099,
        "Median Pity": 13,
        "Won": "26%"
      },
      "5-Star": {
        "Rate": "16.793%",
        "Count": 7069
      },
      "Total Obtained": 661,
      "Featured Image": null
    },
    "Rising Mount Issue": {
      "Total Users": 386,
      "Total Pulls": 14085,
      "Oroberyl Spent": null,
      "6-Star": {
        "Rate": "5.034%",
        "Count": 709,
        "Median Pity": 12,
        "Won": "23%"
      },
      "5-Star": {
        "Rate": "16.471%",
        "Count": 2320
      },
      "Total Obtained": 196,
      "Featured Image": null
    },
    "Thunderous Peal Issue": {
      "Total Users": 274,
      "Total Pulls": 9960,
      "Oroberyl Spent": null,
      "6-Star": {
        "Rate": "4.618%",
        "Count": 460,
        "Median Pity": 12,
        "Won": "24%"
      },
      "5-Star": {
        "Rate": "16.596%",
        "Count": 1653
      },
      "Total Obtained": 135,
      "Featured Image": null
    }
  }
}