{
  "Standard Weapon": {
    "Solid Ice Issue": {
      "Total Users": 1368,
      "Total Pulls": 56408,
      "Oroberyl Spent": null,
      "6-Star": {
        "Rate": "5.058%",
        "Count": 2853,
        "Median Pity": 13,
        "Won": "27%"
      },
      "5-Star": {
        "Rate": "16.811%",
        "Count": 9483
      },
      "Total Obtained": 941,
      "Featured Image": null
    },
    "Cosmic Voice Issue": {
      "Total Users": 3465,
      "Total Pulls": 44753,
      "Oroberyl Spent": null,
      "6-Star": {
        "Rate": "4.181%",
        "Count": 1871,
        "Median Pity": 6,
        "Won": "26%"
      },
      "5-Star": {
        "Rate": "16.531%",
        "Count": 7398
      },
      "Total Obtained": 500,
      "Featured Image": null
    },
    "Far Expedition Issue": {
      "Total Users": 1196,
      "Total Pulls": 51609,
      "Oroberyl Spent": null,
      "6-Star": {
        "Rate": "5.044%",
        "Count": 2603,
        "Median Pity": 12,
        "Won": "25%"
      },
      "5-Star": {
        "Rate": "16.763%",
        "Count": 8651
      },
      "Total Obtained": 815,
      "Featured Image": null
    },
    "Rising Mount Issue": {
      "Total Users": 473,
      "Total Pulls": 17851,
      "Oroberyl Spent": null,
      "6-Star": {
        "Rate": "5.003%",
        "Count": 893,
        "Median Pity": 12,
        "Won": "24%"
      },
      "5-Star": {
        "Rate": "16.425%",
        "Count": 2932
      },
      "Total Obtained": 258,
      "Featured Image": null
    },
    "Thunderous Peal Issue": {
      "Total Users": 332,
      "Total Pulls": 12190,
      "Oroberyl Spent": null,
      "6-Star": {
        "Rate": "4.578%",
        "Count": 558,
        "Median Pity": 12,
        "Won": "24%"
      },
      "5-Star": {
        "Rate": "16.612%",
        "Count": 2025
      },
      "Total Obtained": 166,
      "Featured Image": null
    }
  }
}