{
  "Standard Weapon": {
    "Solid Ice Issue": {
      "Total Users": 1288,
      "Total Pulls": 52944,
      "Oroberyl Spent": null,
      "6-Star": {
        "Rate": "5.070%",
        "Count": 2684,
        "Median Pity": 13,
        "Won": "27%"
      },
      "5-Star": {
        "Rate": "16.827%",
        "Count": 8909
      },
      "Total Obtained": 880,
      "Featured Image": null
    },
    "Cosmic Voice Issue": {
      "Total Users": 3340,
      "Total Pulls": 43063,
      "Oroberyl Spent": null,
      "6-Star": {
        "Rate": "4.192%",
        "Count": 1805,
        "Median Pity": 6,
        "Won": "26%"
      },
      "5-Star": {
        "Rate": "16.494%",
        "Count": 7103
      },
      "Total Obtained": 478,
      "Featured Image": null
    },
    "Far Expedition Issue": {
      "Total Users": 1140,
      "Total Pulls": 49092,
      "Oroberyl Spent": null,
      "6-Star": {
        "Rate": "5.031%",
        "Count": 2470,
        "Median Pity": 13,
        "Won": "25%"
      },
      "5-Star": {
        "Rate": "16.773%",
        "Count": 8234
      },
      "Total Obtained": 771,
      "Featured Image": null
    },
    "Rising Mount Issue": {
      "Total Users": 450,
      "Total Pulls": 16993,
      "Oroberyl Spent": null,
      "6-Star": {
        "Rate": "5.014%",
        "Count": 852,
        "Median Pity": 12,
        "Won": "23%"
      },
      "5-Star": {
        "Rate": "16.424%",
        "Count": 2791
      },
      "Total Obtained": 240,
      "Featured Image": null
    },
    "Thunderous Peal Issue": {
      "Total Users": 318,
      "Total Pulls": 11710,
      "Oroberyl Spent": null,
      "6-Star": {
        "Rate": "4.594%",
        "Count": 538,
        "Median Pity": 12,
        "Won": "24%"
      },
      "5-Star": {
        "Rate": "16.627%",
        "Count": 1947
      },
      "Total Obtained": 159,
      "Featured Image": null
    }
  }
}